spacy_matching/__init__.py
spacy_matching/recoding.py
spacy_matching/utils.py
spacy_matching-0.5.1.dist-info/WHEEL
spacy_matching-0.5.1.dist-info/METADATA
spacy_matching-0.5.1.dist-info/RECORD
