Metadata-Version: 2.3
Name: spacy-matching
Version: 0.5.1
Summary: Add your description here
Keywords: matching,package,cancerdata
Author: msauerberg
Author-email: msauerberg <markus.sauerberg@bwfgb.hamburg.de>
Classifier: License :: OSI Approved :: MIT License
Classifier: Programming Language :: Python :: 3
Classifier: Programming Language :: Python :: 3.12
Classifier: Development Status :: 3 - Alpha
Classifier: Intended Audience :: Science/Research
Classifier: Operating System :: OS Independent
Classifier: Topic :: Scientific/Engineering
Requires-Dist: levenshtein>=0.27.1
Requires-Dist: pandas-plots>=0.16.2
Requires-Dist: pandas>=2.2.3
Requires-Dist: pip>=25.0.1
Requires-Dist: spacy>=3.8.5
Requires-Dist: spaczz>=0.6.1
Maintainer: smeisegeier
Maintainer-email: smeisegeier <meisegeiers@rki.de>
Requires-Python: >=3.11
Project-URL: Bug Tracker, https://github.com/msauerberg/spacy_matching/issues
Project-URL: Homepage, https://github.com/msauerberg/spacy_matching
Project-URL: Repository, https://github.com/msauerberg/spacy_matching
